Resilience/__init.py__.py
Resilience/models.py
Resilience-0.0.1.dist-info/LICENSE
Resilience-0.0.1.dist-info/METADATA
Resilience-0.0.1.dist-info/WHEEL
Resilience-0.0.1.dist-info/top_level.txt
Resilience-0.0.1.dist-info/RECORD
