Metadata-Version: 2.1
Name: Resilience
Version: 0.0.1
Summary: Open source resilience models
Author-email: Pranavesh Panakkal <ppranavesh@gmail.com>
Project-URL: Homepage, https://github.com/pypa/Resilience
Project-URL: Issues, https://github.com/Pranavesh-Panakkal/Resilience/issues
Classifier: Programming Language :: Python :: 3
Classifier: License :: OSI Approved :: MIT License
Classifier: Operating System :: OS Independent
Requires-Python: >=3.8
License-File: LICENSE
